{
  "source_three_rate": 1.75,
  "source_apg": 1.184,
  "source_conference": 1.015,
  "source_conf_power": 0.758,
  "source_ts_pct": 0.677,
  "source_pts_per_40": 0.619,
  "height_in": 0.587,
  "source_fg3_pct": 0.552,
  "source_spg": 0.54,
  "source_ft_pct": 0.496,
  "source_per": 0.384,
  "conf_power_delta": 0.352,
  "source_efg_pct": 0.332,
  "weight_lbs": 0.328,
  "source_blk_per_40": 0.32,
  "source_topg": 0.304,
  "source_tov_per_40": 0.302,
  "source_bpg": 0.292,
  "source_stl_per_40": 0.288,
  "destination_conf_power": 0.284,
  "source_ws": 0.271,
  "source_ft_rate": 0.263,
  "source_usg_pct": 0.251,
  "source_mpg": 0.25,
  "source_reb_per_40": 0.25,
  "source_ast_per_40": 0.25,
  "source_bpm": 0.25,
  "source_minutes_share": 0.25,
  "source_games": 0.25,
  "source_ppg": 0.25,
  "source_fg_pct": 0.25,
  "position": 0.25,
  "source_level": 0.25,
  "source_rpg": 0.25
}
